{
  "id": 10125,
  "type": "monster",
  "name": "Muzurhythm the String Djinn",
  "englishAttribute": "wind",
  "localizedAttribute": "WIND",
  "effectText": "2 Level 3 monsters\nWhen a \"Djinn\" Xyz Monster you control is attacking an opponent's monster, during the Damage Step: You can detach 1 Xyz Material from this card; the attacking monster's ATK is doubled until the End Phase. You can only use this effect of \"Muzurhythm the String Djinn\" once per turn.",
  "rank": 3,
  "atk": 1500,
  "def": 1000,
  "properties": [
    "Fiend",
    "Xyz",
    "Effect"
  ]
}
