{
  "id": 12282,
  "type": "monster",
  "name": "Lunalight White Rabbit",
  "englishAttribute": "dark",
  "localizedAttribute": "DARK",
  "effectText": "When this card is Normal Summoned: You can target 1 \"Lunalight\" monster in your Graveyard, except \"Lunalight White Rabbit\"; Special Summon it in Defense Position. Once per turn: You can target Spell/Trap Cards your opponent controls, up to the number of other \"Lunalight\" cards you control; return them to the hand.",
  "level": 2,
  "atk": 800,
  "def": 800,
  "properties": [
    "Beast-Warrior",
    "Effect"
  ]
}
