{
  "id": 12470,
  "type": "trap",
  "name": "Magician Navigation",
  "englishAttribute": "trap",
  "localizedAttribute": "TRAP",
  "effectText": "Special Summon 1 \"Dark Magician\" from your hand, then Special Summon 1 Level 7 or lower DARK Spellcaster monster from your Deck. If you control \"Dark Magician\", except the turn this card was sent to the GY: You can banish this card from your GY, then target 1 face-up Spell/Trap your opponent controls; negate its effects until the end of this turn."
}
