{
  "id": 15268,
  "type": "monster",
  "name": "Red Potan",
  "englishAttribute": "fire",
  "localizedAttribute": "FIRE",
  "effectText": "You can target 1 \"Potan\" monster you control; treat it as a Tuner until the end of the next turn. If a monster is Synchro Summoned while you control this monster: You can Special Summon 1 \"Potan\" monster from your hand or Deck. You can only use each effect of \"Red Potan\" once per turn.",
  "level": 1,
  "atk": 100,
  "def": 200,
  "properties": [
    "Fairy",
    "Effect"
  ]
}
