{
  "id": 10780,
  "type": "monster",
  "name": "Unermüdlicher Boxer Betrugskommissar",
  "englishAttribute": "fire",
  "localizedAttribute": "FEUER",
  "effectText": "2 Monster der Stufe 3\nAlle Monster, die dein Gegner kontrolliert, müssen angreifen, falls möglich. Solange du ein anderes „Unermüdlicher Boxer“-Monster kontrollierst, können Monster deines Gegners diese Karte nicht als Angriffsziel wählen. Wenn ein Angriff deklariert wird, an dem ein anderes „Unermüdlicher Boxer“-Monster beteiligt ist, das du kontrollierst: Du kannst 2 Material von dieser Karte abhängen; sieh dir die Hand deines Gegners an, dann setze 1 Zauber von seiner Hand auf deine Spielfeldseite.",
  "rank": 3,
  "atk": 0,
  "def": 1300,
  "properties": [
    "Krieger",
    "Xyz",
    "Effekt"
  ]
}
