{
  "id": 12219,
  "type": "monster",
  "name": "Superquantal Mechungeheuer Grampulse",
  "englishAttribute": "water",
  "localizedAttribute": "WASSER",
  "effectText": "2 Monster der Stufe 3\nDiese Karte kann nicht angreifen, es sei denn, sie hat Xyz-Material. Einmal pro Spielzug: Du kannst 1 Xyz-Material von dieser Karte abhängen und dann 1 Zauber-/Fallenkarte auf dem Spielfeld wählen; zerstöre sie. Dieser Effekt kann während des Spielzugs eines beliebigen Spielers aktiviert werden, falls diese Karte „Superquantum Blaue Schicht“ als Xyz-Material hat. Einmal pro Spielzug: Du kannst 1 „Superquantum“-Monster von deiner Hand oder Spielfeldseite als Xyz-Material an diese Karte anhängen.",
  "rank": 3,
  "atk": 1800,
  "def": 2800,
  "properties": [
    "Maschine",
    "Xyz",
    "Effekt"
  ]
}
