{
  "id": 13670,
  "type": "monster",
  "name": "Himmelsjäger-Ass - Raye",
  "englishAttribute": "dark",
  "localizedAttribute": "FINSTERNIS",
  "effectText": "(Schnelleffekt): Du kannst diese Karte als Tribut anbieten; beschwöre 1 „Himmelsjäger-Ass“-Monster als Spezialbeschwörung von deinem Extra Deck in die Extra-Monsterzone. Solange sich diese Karte in deinem Friedhof befindet, falls ein offenes „Himmelsjäger-Ass“-Linkmonster, das du kontrollierst, durch Kampf zerstört wird oder das Spielfeld durch einen Karteneffekt eines Gegners verlässt: Du kannst diese Karte als Spezialbeschwörung beschwören. Du kannst jeden Effekt von „Himmelsjäger-Ass - Raye“ nur einmal pro Spielzug verwenden.",
  "level": 4,
  "atk": 1500,
  "def": 1500,
  "properties": [
    "Krieger",
    "Effekt"
  ]
}
