{
  "id": 14615,
  "type": "monster",
  "name": "Rakketen-Sucher",
  "englishAttribute": "dark",
  "localizedAttribute": "FINSTERNIS",
  "effectText": "(Schnelleffekt): Du kannst 1 offene Karte wählen, die du kontrollierst; zerstöre sie und falls du dies tust, beschwöre 1 „Rakkete“-Monster als Spezialbeschwörung von deinem Deck, außer „Rakketen-Sucher“, zusätzlich kannst du für den Rest dieses Spielzugs keine Monster als Spezialbeschwörung vom Extra Deck beschwören, außer FINSTERNIS Monstern. Du kannst diesen Effekt von „Rakketen-Sucher“ nur einmal pro Spielzug verwenden.",
  "level": 4,
  "atk": 1600,
  "def": 1000,
  "properties": [
    "Drache",
    "Empfänger",
    "Effekt"
  ]
}
