{
  "id": 15010,
  "type": "monster",
  "name": "Girsu, der Orcust-Mekk-Ritter",
  "englishAttribute": "dark",
  "localizedAttribute": "FINSTERNIS",
  "effectText": "Falls diese Karte als Normal- oder Spezialbeschwörung beschworen wird: Du kannst 1 „Orcust“- oder „Weltvermächtnis“-Karte von deinem Deck auf den Friedhof legen, dann, falls 2 oder mehr andere Karten in der Spalte dieser Karte liegen, behandle diese Karte in diesem Spielzug als Empfänger. Falls du keine anderen Monster kontrollierst: Du kannst 1 „Weltvermächtnis-Spielmarke“ (Maschine/FINSTERNIS/Stufe 1/ATK 0/DEF 0) als Spezialbeschwörung auf die Spielfeldseiten beider Spieler in die Verteidigungsposition beschwören. Du kannst jeden Effekt von „Girsu, der Orcust-Mekk-Ritter“ nur einmal pro Spielzug verwenden.",
  "level": 4,
  "atk": 1800,
  "def": 0,
  "properties": [
    "Maschine",
    "Effekt"
  ]
}
