{
  "id": 7526,
  "type": "monster",
  "name": "Geflügelter Kuriboh LV9",
  "englishAttribute": "light",
  "localizedAttribute": "LICHT",
  "effectText": "Aktiviere diesen Effekt nur als Kettenglied 3 oder höher (Schnelleffekt): Du kannst diese Karte als Spezialbeschwörung von deiner Hand beschwören. Zauberkarten, die aktiviert wurden, werden verbannt, anstatt auf den Friedhof gelegt zu werden. Die ATK/DEF dieser Karte entsprechen jeweils der Anzahl Zauber im Friedhof deines Gegners x 500. Du kannst nur 1 „Geflügelter Kuriboh LV9“ kontrollieren.",
  "level": 9,
  "atk": -1,
  "def": -1,
  "properties": [
    "Fee",
    "Effekt"
  ]
}
