{
  "id": 9459,
  "type": "monster",
  "name": "Schwarzflügel - Pinaki der zunehmende Mond",
  "englishAttribute": "dark",
  "localizedAttribute": "FINSTERNIS",
  "effectText": "Kann nicht als Synchromaterial verwendet werden, außer für die Synchrobeschwörung eines „Schwarzflügel“-Synchromonsters. Während der End Phase, falls sich diese Karte im Friedhof befindet, weil sie in diesem Spielzug vom Spielfeld dorthin gelegt wurde: Du kannst deiner Hand 1 „Schwarzflügel“-Monster von deinem Deck hinzufügen, außer „Schwarzflügel - Pinaki der zunehmende Mond“. Du kannst diesen Effekt von „Schwarzflügel - Pinaki der zunehmende Mond“ nur einmal pro Spielzug verwenden.",
  "level": 3,
  "atk": 1200,
  "def": 1000,
  "properties": [
    "Geflügeltes Ungeheuer",
    "Empfänger",
    "Effekt"
  ]
}
