{
  "id": 20544,
  "type": "trap",
  "name": "Ruisseau Vertueux",
  "englishAttribute": "trap",
  "localizedAttribute": "PIÈGE",
  "effectText": "Ciblez 1 monstre Poisson, Serpent de Mer ou Aqua que vous contrôlez et 2 cartes contrôlées par votre adversaire ; détruisez-les. Vous pouvez bannir cette carte depuis votre Cimetière, puis ciblez 1 monstre face recto sur le Terrain ; si c'est un monstre EAU, la prochaine fois qu'il va être détruit par un effet de carte ce tour, il n'est pas détruit. Si ce n'est pas un monstre EAU, il devient EAU. Vous ne pouvez utiliser chaque effet de \"Ruisseau Vertueux\" qu'une fois par tour."
}
