{
  "id": 10989,
  "type": "monster",
  "name": "Nobile Cavaliere Peredur",
  "englishAttribute": "light",
  "localizedAttribute": "LUCE",
  "effectText": "Mentre è equipaggiato con una Carta Magia Equipaggiamento \"Nobili Armi\", questa carta diventa OSCURITÀ e il suo Livello aumenta di 1. Se questa carta viene mandata al Cimitero mentre è equipaggiata con una Carta Magia Equipaggiamento \"Nobili Armi\": scegli come bersaglio 1 carta \"Nobili Armi\" nel tuo Cimitero; aggiungi quel bersaglio alla tua mano.",
  "level": 4,
  "atk": 1900,
  "def": 300,
  "properties": [
    "Guerriero",
    "Effetto"
  ]
}
