{
  "id": 14881,
  "type": "trap",
  "name": "Emergenza Megalito",
  "englishAttribute": "trap",
  "localizedAttribute": "TRAPPOLA",
  "effectText": "Puoi scegliere come bersaglio 1 mostro \"Megalito\" nel tuo Cimitero; Evocalo Specialmente in Posizione di Difesa, ma mettilo in fondo al Deck quando lascia il Terreno (anche se questa carta lascia il Terreno). Puoi utilizzare questo effetto di \"Emergenza Megalito\" una sola volta per turno.",
  "englishProperty": "continuous",
  "localizedProperty": "Continua"
}
