{
  "id": 18189,
  "type": "monster",
  "name": "Drago Fotonico Galattico",
  "englishAttribute": "light",
  "localizedAttribute": "LUCE",
  "effectText": "2 mostri di Livello 4\nGli altri mostri LUCE che controlli guadagnano 500 ATK. Puoi utilizzare ognuno dei seguenti effetti di \"Drago Fotonico Galattico\" una sola volta per turno. Puoi staccare 1 materiale da questa carta; aggiungi 1 carta \"Fotonico\" o \"Galattico\" dal tuo Deck alla tua mano, oppure mandala al Cimitero. Se uno o più mostri LUCE vengono Evocati Specialmente sul tuo Terreno (eccetto durante il Damage Step): puoi scegliere come bersaglio 1 di quei mostri; il suo Livello diventa 4 o 8 fino alla fine di questo turno.",
  "rank": 4,
  "atk": 2000,
  "def": 0,
  "properties": [
    "Drago",
    "Xyz",
    "Effetto"
  ]
}
