{
  "id": 18330,
  "type": "spell",
  "name": "Doppio Attacco! Vento e Tuono!!",
  "englishAttribute": "spell",
  "localizedAttribute": "MAGIA",
  "effectText": "Se controlli un mostro \"Guardiano del Cancello\": scegli come bersaglio 1 carta sul Terreno; distruggila. Durante la tua Main Phase: puoi bandire questa carta dal tuo Cimitero; aggiungi 1 dei tuoi \"Sanga del Tuono\", \"Kazejin\" o \"Suijin\" che è bandito o nel tuo Deck alla tua mano. Puoi utilizzare questo effetto di \"Doppio Attacco! Vento e Tuono!!\" una sola volta per turno.",
  "englishProperty": "quickplay",
  "localizedProperty": "Rapida"
}
