{
  "id": 22154,
  "type": "monster",
  "name": "Salvataggio-ASSO Mediatore",
  "englishAttribute": "fire",
  "localizedAttribute": "FUOCO",
  "effectText": "2+ mostri FUOCO\nPuoi Evocare Specialmente uno o più \"Salvataggio-ASSO Mediatore\" una sola volta per turno. Se questa carta viene Evocata Link: puoi aggiungere 1 \"Salvataggio-ASSO Idrante\" o \"Salvataggio-ASSO QG\" dal tuo Deck o Cimitero alla tua mano. Se attivi una Carta Magia Rapida \"Salvataggio-ASSO\" o una Carta Trappola Normale \"Salvataggio-ASSO\" (eccetto durante il Damage Step): puoi scegliere come bersaglio 1 carta controllata dal tuo avversario; distruggila. Puoi utilizzare questo effetto di \"Salvataggio-ASSO Mediatore\" solo due volte per turno.",
  "linkRating": 4,
  "linkArrows": [
    "4",
    "6",
    "1",
    "3"
  ],
  "atk": 3000,
  "properties": [
    "Macchina",
    "Link",
    "Effetto"
  ]
}
