{
  "id": 9314,
  "type": "monster",
  "name": "Shinai - Sei Samurai Leggendario",
  "englishAttribute": "water",
  "localizedAttribute": "ACQUA",
  "effectText": "Se controlli \"Mizuho - Sei Samurai Leggendario\", puoi Evocare Specialmente questa carta (dalla tua mano). Se questa carta sul Terreno viene offerta come Tributo: scegli come bersaglio 1 mostro \"Sei Samurai\" nel tuo Cimitero, eccetto \"Shinai - Sei Samurai Leggendario\"; aggiungilo alla tua mano.",
  "level": 3,
  "atk": 1500,
  "def": 1500,
  "properties": [
    "Guerriero",
    "Effetto"
  ]
}
