{
  "id": 17792,
  "type": "monster",
  "name": "Silent Wolf Calupo",
  "englishAttribute": "dark",
  "localizedAttribute": "DARK",
  "effectText": "If this card is Normal or Special Summoned: Equip the top card of your Deck to this card as a face-down Equip Spell that gives it 500 ATK. During the End Phase: Your opponent calls the original type (Monster, Spell, or Trap) of that Equip Card equipped by this card's effect. If they called it right, send this card to the GY. If they called it wrong, discard 1 random card from your opponent's hand, and if you do, return this card to the hand. You can only use this effect of \"Silent Wolf Calupo\" once per turn.",
  "level": 4,
  "atk": 1400,
  "def": 1400,
  "properties": [
    "Beast-Warrior",
    "Effect"
  ]
}
