{
  "id": 20480,
  "type": "monster",
  "name": "Heart of the Blue-Eyes",
  "englishAttribute": "light",
  "localizedAttribute": "LIGHT",
  "effectText": "(This card is always treated as a \"Millennium\" card.)\nControl of this card cannot switch. You can discard this card; add 1 \"Millennium Ankh\" from your Deck to your hand. You can only use this effect of \"Heart of the Blue-Eyes\" once per turn. If this card is in your GY, and you have successfully activated \"Millennium Ankh\" this Duel, and your opponent Normal or Special Summons a monster(s) that is Level 8 or higher, or has 3000 or more ATK: You can send that monster to the GY, and if you do, Special Summon this card. You can only use this effect of \"Heart of the Blue-Eyes\" once per Duel.",
  "level": 8,
  "atk": 3000,
  "def": 2500,
  "properties": [
    "Dragon",
    "Effect"
  ]
}
