{
  "id": 5377,
  "type": "monster",
  "name": "Yamata Dragon",
  "englishAttribute": "fire",
  "localizedAttribute": "FIRE",
  "effectText": "Cannot be Special Summoned. If this card inflicts battle damage to your opponent: Draw until you have 5 cards in your hand. Once per turn, during the End Phase, if this card was Normal Summoned or flipped face-up this turn: Return this card to the hand.",
  "level": 7,
  "atk": 2600,
  "def": 3100,
  "properties": [
    "Dragon",
    "Spirit",
    "Effect"
  ]
}
