{
  "id": 10844,
  "type": "monster",
  "name": "ZW - Armadura Sleipnir",
  "englishAttribute": "light",
  "localizedAttribute": "LUZ",
  "effectText": "Puedes seleccionar 1 monstruo \"Utopía\" que controles; equipa a ese objetivo este monstruo en tu mano o lado del Campo. Ese objetivo gana 1000 ATK. Cuando esta carta que controlas es mandada a tu Cementerio porque el monstruo equipado fue destruido por una carta de tu adversario (en batalla o por efecto de una carta): puedes seleccionar 1 monstruo \"Utopía\" en tu Cementerio; Invoca ese objetivo de Modo Especial. Sólo puedes controlar 1 \"ZW - Armadura Sleipnir\".",
  "level": 4,
  "atk": 1000,
  "def": 1000,
  "properties": [
    "Bestia",
    "Efecto"
  ]
}
