{
  "id": 12262,
  "type": "monster",
  "name": "Número 84: Gainer del Dolor",
  "englishAttribute": "dark",
  "localizedAttribute": "OSCURIDAD",
  "effectText": "2 monstruos de Nivel 11\nTambién puedes Invocar Xyz esta carta usando un Monstruo Xyz de OSCURIDAD de Rango 8, 9, o 10 que controles que tenga 2 o más materiales. (Transfiere sus materiales a esta carta). Gana DEF igual a los Rangos combinados de todos los Monstruos Xyz que controles x 200. Mientras esta carta tenga material, cada vez que tu adversario active una Carta Mágica/de Trampa, inflige 600 puntos de daño a tu adversario inmediatamente después de que ésta se resuelva. Una vez por turno: puedes desacoplar 1 material de esta carta; destruye todos los monstruos boca arriba que controle tu adversario con DEF igual o menor a la de esta carta.",
  "rank": 11,
  "atk": 0,
  "def": 0,
  "properties": [
    "Insecto",
    "Xyz",
    "Efecto"
  ]
}
