{
  "id": 12359,
  "type": "monster",
  "name": "Dragón Arcavaliente",
  "englishAttribute": "light",
  "localizedAttribute": "LUZ",
  "effectText": "Si esta carta es Invocada de Modo Especial desde el Cementerio: puedes desterrar tantas Mágicas/Trampas boca arriba que controle tu adversario como sea posible y, si lo haces, esta carta gana 200 ATK/DEF por cada carta desterrada. Una vez por turno, durante la Standby Phase, si esta carta está en el Cementerio porque fue mandada ahí el último turno: puedes seleccionar 1 monstruo Dragón de Nivel 7 u 8 en tu Cementerio, excepto \"Dragón Arcavaliente\"; Invócalo de Modo Especial.",
  "level": 7,
  "atk": 2400,
  "def": 2000,
  "properties": [
    "Dragón",
    "Efecto"
  ]
}
