{
  "id": 12976,
  "type": "spell",
  "name": "B.E.F. Zelos",
  "englishAttribute": "spell",
  "localizedAttribute": "MÁGICA",
  "effectText": "Cuando esta carta es activada: puedes añadir a tu mano 1 \"Apuro de Jefes\" en tu Deck. Los monstruos \"B.E.S.\" que controlas ganan 500 ATK/DEF, tu adversario no puede seleccionarlos con efectos de cartas, y además no pueden ser destruidos por efectos de cartas de tu adversario. Una vez por turno: puedes Invocar de Modo Especial 1 monstruo \"B.E.S.\" desde tu mano. Si uno o más monstruos \"B.E.S.\" son Invocados de Modo Normal o Especial a tu Campo: pon 1 contador en cada uno de ellos.",
  "englishProperty": "field",
  "localizedProperty": "Campo"
}
