{
  "id": 15831,
  "type": "monster",
  "name": "Hexa Espíritu de la Barrera de Hielo",
  "englishAttribute": "water",
  "localizedAttribute": "AGUA",
  "effectText": "Mientras controles otro monstruo \"Barrera de Hielo\", los monstruos que controle tu adversario pierden 500 ATK/DEF. Durante tu Main Phase: puedes mandar al Cementerio 1 monstruo \"Barrera de Hielo\" de Nivel 3 o menor en tu Deck y, si lo haces, hasta el final de este turno el Nivel de esta carta se convierte en el mismo que el de ese monstruo. Sólo puedes usar este efecto de \"Hexa Espíritu de la Barrera de Hielo\" una vez por turno.",
  "level": 1,
  "atk": 400,
  "def": 200,
  "properties": [
    "Serpiente Marina",
    "Cantante",
    "Efecto"
  ]
}
