{
  "id": 17174,
  "type": "spell",
  "name": "El Pronóstico Meteorológico",
  "englishAttribute": "spell",
  "localizedAttribute": "MÁGICA",
  "effectText": "Cuando esta carta es activada: puedes poner boca arriba en tu Zona de Magia y Trampas 1 Mágica/Trampa \"Meteorológico/a\" en tu Deck. Sólo puedes usar cada uno de los siguientes efectos de \"El Pronóstico Meteorológico\" una vez por turno. Si Invocas por Enlace un Monstruo de Enlace \"Meteorológico/a\", también puedes usar cartas \"Meteorológico/a\" boca arriba en tu Zona de Magia y Trampas como monstruos \"Meteorológico/a\" para su Invocación por Enlace. Durante tu Main Phase, puedes: inmediatamente después de que se resuelva este efecto, Invoca de Modo Normal 1 monstruo \"Meteorológico/a\" desde tu mano. Sólo puedes activar 1 \"El Pronóstico Meteorológico\" por turno.",
  "englishProperty": "field",
  "localizedProperty": "Campo"
}
