{
  "id": 17658,
  "type": "monster",
  "name": "G Gólem Corazón de Cristal",
  "englishAttribute": "water",
  "localizedAttribute": "AGUA",
  "effectText": "2 monstruos Ciberso\nPuedes seleccionar 1 Monstruo de Enlace de TIERRA en tu Cementerio; Invócalo de Modo Especial a tu zona a la que apunte esta carta y, si lo haces, pon 1 Contador GG en esta carta. Sólo puedes usar este efecto de \"G Gólem Corazón de Cristal\" una vez por turno. Los monstruos de TIERRA co-enlazados a esta carta ganan 600 ATK por cada Contador GG en esta carta, pueden hacer un segundo ataque durante cada Battle Phase y además, si atacan a un monstruo en Posición de Defensa, infligen daño de batalla de penetración a tu adversario.",
  "linkRating": 2,
  "linkArrows": [
    "4",
    "2"
  ],
  "atk": 0,
  "properties": [
    "Ciberso",
    "Enlace",
    "Efecto"
  ]
}
