{
  "id": 12676,
  "type": "monster",
  "name": "앤틱 기어 리액터 드래곤",
  "englishAttribute": "earth",
  "localizedAttribute": "땅",
  "effectText": "①: \"앤틱 기어\" 몬스터를 릴리스하고 어드밴스 소환한 이 카드가 수비 표시 몬스터를 공격했을 경우, 그 수비력을 공격력이 넘은 만큼만 전투 데미지를 준다. ②: \"가제트\" 몬스터를 릴리스하고 어드밴스 소환한 이 카드는 1번의 배틀 페이즈 중에 2회 공격할 수 있다. ③: 이 카드가 공격할 경우, 상대는 데미지 스텝 종료시까지 몬스터의 효과 / 마법 / 함정 카드를 발동할 수 없다. ④: 이 카드가 공격한 데미지 스텝 종료시에 발동할 수 있다. 필드의 마법 / 함정 카드 1장을 고르고 파괴한다.",
  "level": 9,
  "atk": 3000,
  "def": 3000,
  "properties": [
    "기계족",
    "효과"
  ]
}
