{
  "id": 12835,
  "type": "monster",
  "name": "프레데터 플랜츠 키메라플레시아",
  "englishAttribute": "dark",
  "localizedAttribute": "어둠",
  "effectText": "\"프레데터 플랜츠\" 몬스터 ＋ 어둠 속성 몬스터\n①: 1턴에 1번, 이 카드의 레벨 이하의 레벨을 가지는 필드의 몬스터 1장을 대상으로 하고 발동할 수 있다. 그 몬스터를 제외한다. ②: 이 카드가 상대의 앞면 표시 몬스터와 전투를 실행하는 공격 선언시에 발동할 수 있다. 턴 종료시까지, 그 상대 몬스터의 공격력은 1000 내리고, 이 카드의 공격력은 1000 올린다. ③: 이 카드가 묘지로 보내졌을 경우, 다음 스탠바이 페이즈에 발동할 수 있다. 덱에서 \"융합\" 마법 카드 또는 \"퓨전\" 마법 카드 1장을 패에 넣는다.",
  "level": 7,
  "atk": 2500,
  "def": 2000,
  "properties": [
    "식물족",
    "융합",
    "효과"
  ]
}
