{
  "id": 20525,
  "type": "spell",
  "name": "Annuncio Reincarnazione Maglia",
  "englishAttribute": "spell",
  "localizedAttribute": "MAGIA",
  "effectText": "(Questa carta viene sempre considerata come una carta \"Corazzato Xyz\".)\nUn Mostro Xyz equipaggiato con questa carta guadagna questi effetti.\n●Non può essere distrutto in battaglia.\n●Una volta per turno, se questa carta ha combattuto in questo turno (Effetto Rapido): puoi far ritornare 1 carta equipaggiata a questa carta nella mano, poi immediatamente dopo che questo effetto si è risolto, Evoca Xyz 1 Mostro Xyz ACQUA.\nUna volta per turno, durante la End Phase, se questa carta è nel Cimitero perché è stata mandata lì in questo turno: puoi equipaggiare questa carta a 1 Mostro Xyz che controlli. Puoi attivare solo 1 \"Annuncio Reincarnazione Maglia\" per turno.",
  "englishProperty": "equip",
  "localizedProperty": "Equipaggiamento"
}
