{
  "id": 10870,
  "type": "monster",
  "name": "Dragão Cibernético Nova",
  "englishAttribute": "light",
  "localizedAttribute": "LUZ",
  "effectText": "2 monstros Máquina de Nível 5\nUma vez por turno: você pode desassociar 1 matéria deste card e, depois, escolha 1 \"Dragão Cibernético\" no seu Cemitério; Invoque o alvo por Invocação-Especial. Uma vez por turno (Efeito Rápido): você pode banir 1 \"Dragão Cibernético\" da sua mão ou da sua Zona de Monstros com a face para cima; este card ganha 2100 de ATK até o final deste turno. Se este card em sua posse for enviado para o seu Cemitério por um efeito de card do seu oponente: você pode Invocar por Invocação-Especial 1 Monstro de Fusão Máquina do seu Deck Adicional.",
  "rank": 5,
  "atk": 2100,
  "def": 1600,
  "properties": [
    "Máquina",
    "Xyz",
    "Efeito"
  ]
}
