{
  "id": 12458,
  "type": "spell",
  "name": "Magia Negra Expandida",
  "englishAttribute": "spell",
  "localizedAttribute": "MAGIA",
  "effectText": "Aplique esses efeitos em sequência, de acordo com o número de \"Mago Negro\" e/ou \"Pequena Maga Negra\" no campo e nos Cemitérios.\n●1+: 1 monstro Mago de TREVAS no campo ganha 1000 de ATK até o final deste turno.\n●2+: Neste turno, seu oponente não pode ativar cards e efeitos em resposta à ativação dos seus Cards ou efeitos de Magia/Armadilha e, além disso, Magias/Armadilhas que você controla não podem ser destruídas pelos efeitos de card do seu oponente.\n●3+: Até o final deste turno, monstros Mago de TREVAS que você controla atualmente não são afetados pelos efeitos de card do seu oponente.",
  "englishProperty": "quickplay",
  "localizedProperty": "Rápida"
}
