{
  "id": 13615,
  "type": "spell",
  "name": "Restauração dos Monarcas",
  "englishAttribute": "spell",
  "localizedAttribute": "MAGIA",
  "effectText": "Ative este card ao escolher 1 monstro no seu Cemitério com 2400 ATK/1000 DEF, ou 2800 ATK/1000 DEF; Invoque-o por Invocação-Especial em Posição de Defesa, mas negue seus efeitos e, além disso, equipe-o com este card. Quando este card deixar o campo, destrua esse monstro. O monstro equipado pode ser considerado como 2 Tributos para uma Invocação-Tributo. Você só pode ativar 1 \"Restauração dos Monarcas\" por turno.",
  "englishProperty": "equip",
  "localizedProperty": "Equipamento"
}
