{
  "id": 14098,
  "type": "monster",
  "name": "Cavaleira do Pesadelo Orcust",
  "englishAttribute": "dark",
  "localizedAttribute": "TREVAS",
  "effectText": "Não pode ser destruído em batalha com um Monstro Link. Você pode banir este card do seu Cemitério e, depois, escolher 1 monstro com a face para cima no campo; pelo resto deste turno você não pode Invocar monstros por Invocação-Especial, exceto monstros de TREVAS e, além disso, envie 1 monstro Máquina de TREVAS do seu Deck para o Cemitério, exceto \"Cavaleira do Pesadelo Orcust\" e, se isso acontecer, até o final deste turno, o monstro alvo ganha ATK igual ao Nível do monstro enviado para o Cemitério x 100. Você só pode usar este efeito de \"Cavaleira do Pesadelo Orcust\" uma vez por turno.",
  "level": 7,
  "atk": 100,
  "def": 2000,
  "properties": [
    "Máquina",
    "Efeito"
  ]
}
