{
  "id": 14987,
  "type": "monster",
  "name": "Paralelo eXcede",
  "englishAttribute": "wind",
  "localizedAttribute": "VENTO",
  "effectText": "Se este card for Invocado por Invocação-Especial pelo efeito de \"Paralelo eXcede\", seu Nível se torna 4 e seu ATK/DEF originais são diminuídos pela metade. Você só pode usar cada um dos seguintes efeitos de \"Paralelo eXcede\" uma vez por turno.\n●Se você Invocar por Invocação-Link: você pode Invocar este card por Invocação-Especial da sua mão em uma zona sua para a qual esse Monstro Link apontar.\n●Se este card for Invocado por Invocação-Normal ou Especial: você pode Invocar por Invocação-Especial 1 \"Paralelo eXcede\" do seu Deck.",
  "level": 8,
  "atk": 2000,
  "def": 2000,
  "properties": [
    "Ciberso",
    "Efeito"
  ]
}
