{
  "id": 15294,
  "type": "spell",
  "name": "Saga dos Guerreiros Antigos - Ventos do Sudeste",
  "englishAttribute": "spell",
  "localizedAttribute": "MAGIA",
  "effectText": "Você deve enviar este card para o Cemitério durante sua 2ª Fase de Apoio depois da ativação. Uma vez por turno, durante sua Fase Principal: lance uma moeda e se o resultado for cara, envie este card para o Cemitério. Se este card for enviado da Zona de Magias & Armadilhas para o Cemitério: você pode ativar este efeito; neste turno, seu oponente não pode ativar cards ou efeitos em resposta à ativação dos seus cards e efeitos \"Guerreiros Antigos\" e, além disso, até o final do turno, todos os Monstros de Efeito \"Guerreiros Antigos\" que você controla atualmente ganham este efeito.\n●Quando este card declarar um ataque: você pode destruir 1 card que seu oponente controla.",
  "englishProperty": "continuous",
  "localizedProperty": "Contínua"
}
