{
  "id": 17638,
  "type": "monster",
  "name": "Caveira de Cristal",
  "englishAttribute": "water",
  "localizedAttribute": "ÁGUA",
  "effectText": "Se este card for Invocado: sofra 1000 de dano e, depois, coloque este card em Posição de Defesa. Durante a Fase Final, se você não sofreu dano de efeito neste turno: você pode adicionar à sua mão ou Invocar por Invocação-Especial 1 monstro Rocha com 0 de ATK do seu Deck. Você só pode usar este efeito de \"Caveira de Cristal\" uma vez por turno.",
  "level": 1,
  "atk": 0,
  "def": 0,
  "properties": [
    "Rocha",
    "Efeito"
  ]
}
