{
  "id": 17650,
  "type": "trap",
  "name": "Livro de Rabiscos - Uh uh uh!",
  "englishAttribute": "trap",
  "localizedAttribute": "ARMADILHA",
  "effectText": "Quando um monstro Dinossauro seu for escolhido como alvo de um ataque: negue o ataque e, depois, você pode Invocar por Invocação-Especial 1 monstro \"Besta de Rabiscos\" do seu Cemitério. Ele não pode ser destruído em batalha e, além disso, destrua-o durante a Fase Final. Se este card estiver no seu Cemitério, exceto no turno em que foi enviado para lá: você pode banir este card do seu Cemitério; adicione 1 monstro Dinossauro de Nível 5 ou mais do seu Deck à sua mão. Você só pode usar cada efeito de \"Livro de Rabiscos - Uh uh uh!\" uma vez por turno."
}
