{
  "id": 19179,
  "type": "monster",
  "name": "Mannadium Trisukta",
  "englishAttribute": "light",
  "localizedAttribute": "LUZ",
  "effectText": "1 Regulador + 1+ monstros não-Reguladores\nSe este card for Invocado por Invocação-Sincro: você pode escolher 1 Regulador de Nível 2 no seu Cemitério; Invoque-o por Invocação-Especial, mas negue seus efeitos. Você pode escolher qualquer número de Reguladores que você controla; mude o Nível deles para 2 e, além disso, você não pode Invocar por Invocação-Especial do Deck Adicional pelo resto deste turno, exceto Monstros Sincro. Você só pode usar cada efeito de \"Mannadium Trisukta\" uma vez por turno.",
  "level": 6,
  "atk": 2300,
  "def": 1300,
  "properties": [
    "Fada",
    "Sincro",
    "Regulador",
    "Efeito"
  ]
}
