{
  "id": 19626,
  "type": "monster",
  "name": "Turing Genex-R",
  "englishAttribute": "dark",
  "localizedAttribute": "TREVAS",
  "effectText": "Durante a Fase Principal do seu oponente, se você controlar um monstro \"Genex\" (Efeito Rápido): você pode Invocar este card por Invocação-Especial da sua mão e, depois, imediatamente depois que este efeito resolver, você pode Invocar por Invocação-Sincro 1 Monstro Sincro \"Genex\". Você só pode usar este efeito de \"Turing Genex-R\" uma vez por turno. Este card no campo pode ser considerado como um monstro de Nível 1 ou 3 quando usado para uma Invocação-Sincro de um Monstro Sincro \"Genex\".",
  "level": 2,
  "atk": 600,
  "def": 600,
  "properties": [
    "Mago",
    "Regulador",
    "Efeito"
  ]
}
