{
  "id": 20532,
  "type": "spell",
  "name": "Flagelo da Floresta Branca",
  "englishAttribute": "spell",
  "localizedAttribute": "MAGIA",
  "effectText": "Ofereça como Tributo 1 Monstro Sincro e, depois, escolha 1 card com a face para cima no campo; negue seus efeitos (até o final deste turno) e, depois, se você ofereceu como Tributo um Monstro Sincro \"Floresta Branca\" para ativar este efeito, você pode Invocar por Invocação-Especial 1 monstro Ilusão do seu Cemitério. Se este card for enviado para o Cemitério para ativar um efeito de monstro: você pode Baixar este card. Você só pode usar cada efeito de \"Flagelo da Floresta Branca\" uma vez por turno.",
  "englishProperty": "quickplay",
  "localizedProperty": "Rápida"
}
