{
  "id": 22086,
  "type": "monster",
  "name": "Portador da Lei Dogmatika",
  "englishAttribute": "light",
  "localizedAttribute": "LUZ",
  "effectText": "Se um monstro Invocado por Invocação-Especial do Deck Adicional estiver no campo e este card estiver na sua mão: você pode Invocar este card por Invocação-Especial. Se este card for Invocado por Invocação-Especial da mão: você pode fazer com que cada duelista envie 1 monstro do Deck Adicional dele para o Cemitério. Se este card for enviado para o Cemitério: você pode escolher 1 card \"Dogmatika\" no seu Cemitério, exceto \"Portador da Lei Dogmatika\"; adicione-o à sua mão. Você só pode usar cada efeito de \"Portador da Lei Dogmatika\" uma vez por turno.",
  "level": 8,
  "atk": 2000,
  "def": 2000,
  "properties": [
    "Mago",
    "Efeito"
  ]
}
