{
  "id": 12694,
  "type": "monster",
  "name": "Dangereux - HÉROS de la Destinée",
  "englishAttribute": "dark",
  "localizedAttribute": "TÉNÈBRES",
  "effectText": "1 monstre \"HÉROS de la Destinée\" + 1 Monstre à Effet TÉNÈBRES\n(Effet Rapide) : vous pouvez défausser 1 carte ; envoyez 1 monstre \"HÉROS de la Destinée\" depuis votre main ou Deck au Cimetière, et si vous le faites, les monstres \"HÉROS de la Destinée\" que vous contrôlez gagnent 200 ATK pour chaque monstre \"HÉROS de la Destinée\" dans votre Cimetière jusqu'à la fin de ce tour. Vous ne pouvez utiliser cet effet de \"Dangereux - HÉROS de la Destinée\" qu'une fois par tour.",
  "level": 6,
  "atk": 2000,
  "def": 2600,
  "properties": [
    "Guerrier",
    "Fusion",
    "Effet"
  ]
}
