{
  "id": 13886,
  "type": "spell",
  "name": "Fête du Lien",
  "englishAttribute": "spell",
  "localizedAttribute": "MAGIE",
  "effectText": "Appliquez cet effet selon le nombre d'Attributs d'origine différents des Monstres Lien sur le Terrain.\n●1 : Tous les Monstres Lien que vous contrôlez gagnent 500 ATK.\n●2 : Tous les Monstres Lien contrôlés par votre adversaire perdent 1000 ATK.\n●3 : Gagnez 1500 LP.\n●4 : Infligez 2000 points de dommages à votre adversaire.\n●5 : Invoquez Spécialement 1 monstre avec min. 2500 ATK depuis votre Deck.\n●6 : Détruisez tous les monstres contrôlés par votre adversaire avec max. 3000 ATK.\nVous ne pouvez activer qu'1 \"Fête du Lien\" par tour."
}
