{
  "id": 15737,
  "type": "monster",
  "name": "Vaisseau Springans - Exblowrer",
  "englishAttribute": "fire",
  "localizedAttribute": "FEU",
  "effectText": "2+ monstres de Niveau 8\nVous pouvez choisir 1 des Zones Monstre ou Zones Magie & Piège de votre adversaire ; détachez un nombre de votre choix de Matériels de cette carte, et si vous le faites, détruisez le même nombre de cartes contrôlées par votre adversaire dans la zone choisie et dans ses Zones Monstre et/ou Zones Magie & Piège adjacentes. Durant la Main ou Battle Phase de votre adversaire (Effet Rapide) : jusqu'à la End Phase, vous pouvez bannir cette carte. Vous ne pouvez utiliser chaque effet de \"Vaisseau Springans - Exblowrer\" qu'une fois par tour.",
  "rank": 8,
  "atk": 1600,
  "def": 2500,
  "properties": [
    "Machine",
    "Xyz",
    "Effet"
  ]
}
