{
  "id": 16435,
  "type": "spell",
  "name": "Combativité A.I.",
  "englishAttribute": "spell",
  "localizedAttribute": "MAGIE",
  "effectText": "Ciblez 1 monstre \"@Ignister\" dans votre Cimetière ; Invoquez-le Spécialement. Si un ou plusieurs monstres \"@Ignister\" que vous contrôlez avec min. 2300 ATK vont être détruits par un effet de carte, vous pouvez bannir cette carte depuis votre Cimetière à la place. Si cette carte est bannie : vous pouvez activer cet effet ; ce tour, vos monstres \"@Ignister\" avec min. 2300 ATK ne peuvent pas être détruits au combat. Vous ne pouvez activer \"Combativité A.I.\" qu'une fois par tour."
}
