{
  "id": 22173,
  "type": "trap",
  "name": "Notes Elfiques : Rhapsodie de la Folie",
  "englishAttribute": "trap",
  "localizedAttribute": "PIÈGE",
  "effectText": "Tant que vous contrôlez un monstre dans votre Zone Monstre Main centrale, les monstres de votre adversaire ne peuvent pas attaquer, sauf pour attaquer le monstre. Vous pouvez envoyer 1 monstre depuis votre main ou Terrain au Cimetière, puis ciblez 1 monstre \"Notes Elfiques\" dans votre Cimetière d'Attribut d'origine différent ; Invoquez-le Spécialement, puis si vous contrôlez un Monstre Synchro, vous pouvez annuler les effets d'1 carte face recto contrôlée par votre adversaire jusqu'à la fin de ce tour. Vous ne pouvez utiliser cet effet de \"Notes Elfiques : Rhapsodie de la Folie\" qu'une fois par tour.",
  "englishProperty": "continuous",
  "localizedProperty": "Continu"
}
