{
  "id": 6871,
  "type": "monster",
  "name": "Reine Charmeuse LV5",
  "englishAttribute": "dark",
  "localizedAttribute": "TÉNÈBRES",
  "effectText": "Une fois par tour, si vous contrôlez cette carte qui a été Invoquée Spécialement par l'effet de \"Reine Charmeuse LV3\" : vous pouvez cibler 1 monstre de max. Niveau 5 contrôlé par votre adversaire ; équipez la cible à cette carte comme Magie d'Équipement (max. 1). Si cette carte va être détruite au combat, détruisez le monstre équipé à la place. Durant votre Standby Phase : vous pouvez envoyer cette carte équipée avec un monstre par l'effet de cette carte au Cimetière ; Invoquez Spécialement 1 \"Reine Charmeuse LV7\" depuis votre main ou Deck.",
  "level": 5,
  "atk": 1000,
  "def": 1000,
  "properties": [
    "Magicien",
    "Effet"
  ]
}
