{
  "id": 8165,
  "type": "monster",
  "name": "Aile Noire - Elphin le Corbeau Funeste",
  "englishAttribute": "dark",
  "localizedAttribute": "TÉNÈBRES",
  "effectText": "Si vous contrôlez un monstre \"Aile Noire\", vous pouvez Invoquer Normalement cette carte sans Sacrifice. Lorsque cette carte est Invoquée Normalement : vous pouvez cibler 1 monstre contrôlé par votre adversaire ; changez la position de combat de la cible.",
  "level": 6,
  "atk": 2200,
  "def": 1200,
  "properties": [
    "Bête Ailée",
    "Effet"
  ]
}
