{
  "id": 9879,
  "type": "monster",
  "name": "ZW - Lance Unicorne",
  "englishAttribute": "light",
  "localizedAttribute": "LUMIÈRE",
  "effectText": "Vous pouvez cibler 1 \"Numéro C39 : Rayon Utopie\" que vous contrôlez ; équipez cette carte depuis votre main à la cible. Il gagne 1900 ATK. Si le monstre équipé combat un monstre de votre adversaire, durant la Battle Phase uniquement, les effets du monstre de votre adversaire sont annulés. Vous ne pouvez contrôler qu'1 \"ZW - Lance Unicorne\".",
  "level": 4,
  "atk": 1900,
  "def": 0,
  "properties": [
    "Bête",
    "Effet"
  ]
}
