{
  "id": 11764,
  "type": "monster",
  "name": "キメラテック・ランページ・ドラゴン",
  "nameRuby": "キメラテック・ランページ・ドラゴン",
  "englishAttribute": "dark",
  "localizedAttribute": "闇属性",
  "effectText": "「サイバー・ドラゴン」モンスター×２体以上\nこのカードの融合召喚は上記のカードでしか行えない。\n①：このカードが融合召喚した時、このカードの融合素材としたモンスターの数までフィールドの魔法・罠カードを対象として発動できる。そのカードを破壊する。\n②：１ターンに１度、自分メインフェイズに発動できる。デッキから機械族・光属性モンスターを２体まで墓地へ送る。このターン、このカードは通常の攻撃に加えて、この効果で墓地へ送ったモンスターの数まで１度のバトルフェイズ中に攻撃できる。",
  "level": 5,
  "atk": 2100,
  "def": 1600,
  "properties": [
    "機械族",
    "融合",
    "効果"
  ]
}
