{
  "id": 15879,
  "type": "monster",
  "name": "フリント・クラッガー",
  "nameRuby": "フリント・クラッガー",
  "englishAttribute": "earth",
  "localizedAttribute": "地属性",
  "effectText": "このカード名の①②の効果はそれぞれ１ターンに１度しか使用できない。①：このカードが特殊召喚に成功した場合に発動できる。自分の手札を１枚選んで捨て、EXデッキから「化石」融合モンスター１体を墓地へ送る。②：フィールドのこのカードを墓地へ送って発動できる。相手に５００ダメージを与える。自分の墓地に「化石融合－フォッシル・フュージョン」が存在する場合、さらに除外されている自分の、「化石融合－フォッシル・フュージョン」１枚またはそのカード名が記されたカード１枚を選んで墓地に戻す事ができる。",
  "level": 3,
  "atk": 800,
  "def": 1600,
  "properties": [
    "岩石族",
    "効果"
  ]
}
