{
  "id": 16742,
  "type": "monster",
  "name": "エクソシスター・ジブリーヌ",
  "nameRuby": "エクソシスター・ジブリーヌ",
  "englishAttribute": "light",
  "localizedAttribute": "光属性",
  "effectText": "レベル４モンスター×２\nこのカード名の①③の効果はそれぞれ１ターンに１度しか使用できない。①：「エクソシスター」モンスターを素材としてこのカードのX召喚に成功した自分・相手ターンに、相手フィールドの効果モンスター１体を対象として発動できる。そのモンスターの効果をターン終了時まで無効にする。②：このカードは墓地から特殊召喚されたモンスターが発動した効果では破壊されない。③：このカードのX素材を１つ取り除いて発動できる。このターン中は自分フィールドのXモンスターの攻撃力が８００アップする。",
  "rank": 4,
  "atk": 1400,
  "def": 2800,
  "properties": [
    "戦士族",
    "エクシーズ",
    "効果"
  ]
}
