{
  "id": 20191,
  "type": "monster",
  "name": "鎧騎士竜－ナイト・アームド・ドラゴン－",
  "nameRuby": "よろいきしりゅう－ナイト・アームド・ドラゴン－",
  "englishAttribute": "wind",
  "localizedAttribute": "風属性",
  "effectText": "このカード名の①②③の効果はそれぞれ１ターンに１度しか使用できない。\n①：自分がレベル５以上のドラゴン族モンスターを特殊召喚した場合に発動できる。このカードを手札から特殊召喚する。\n②：このカードが特殊召喚した場合に発動できる。このカードの属性・レベルは、自分の除外状態のドラゴン族モンスター１体と同じになる。\n③：このカードが墓地へ送られた場合、自分フィールドのドラゴン族モンスター１体を対象として発動できる（この効果の発動に対してお互いは効果を発動できない）。そのモンスターの攻撃力は１０００アップする。",
  "level": 3,
  "atk": 1400,
  "def": 1900,
  "properties": [
    "ドラゴン族",
    "効果"
  ]
}
